mute_mic/__init__.py
mute_mic-0.1.0.dist-info/METADATA
mute_mic-0.1.0.dist-info/WHEEL
mute_mic-0.1.0.dist-info/entry_points.txt
mute_mic-0.1.0.dist-info/licenses/LICENSE
mute_mic-0.1.0.dist-info/RECORD
