Metadata-Version: 2.4
Name: mute-mic
Version: 0.1.0
Summary: Small command to (un)mute the mic in Windows
Project-URL: Repository, https://github.com/mrijken/mute-mic
Author-email: Marc Rijken <marc@rijken.org>
License-Expression: MIT AND (Apache-2.0 OR BSD-2-Clause)
License-File: LICENSE
Requires-Python: >=3.10
Requires-Dist: pywin32>=311
